tests/__init__.py
tests/conftest.py
tests/test_api.py
tiny_web/__init__.py
tiny_web/api.py
tiny_web/middleware.py
tiny_web/response.py
tiny_web-0.0.4.dist-info/METADATA
tiny_web-0.0.4.dist-info/WHEEL
tiny_web-0.0.4.dist-info/top_level.txt
tiny_web-0.0.4.dist-info/RECORD
