Metadata-Version: 2.1
Name: tiny-web
Version: 0.0.4
Summary: WSGI-compatible framework to learn how to create tiny web applications
Home-page: UNKNOWN
Author: Sergey Shevtsov
Author-email: dev.serzh@gmail.com
License: MIT
Platform: UNKNOWN
Classifier: Programming Language :: Python :: 3.6
Requires-Python: >=3.6.0
Requires-Dist: jinja2 (==2.11.2)
Requires-Dist: markupsafe (==1.1.1)
Requires-Dist: parse (==1.15.0)
Requires-Dist: webob (==1.8.6)
Requires-Dist: whitenoise (==5.0.1)
Requires-Dist: requests (==2.23.0)
Requires-Dist: requests-wsgi-adapter (==0.4.1)
